gemini_unwatermark/__init__.py
gemini_unwatermark/cli.py
gemini_unwatermark/model.py
gemini_unwatermark/processor.py
gemini_unwatermark/utils.py
gemini_unwatermark-0.1.1.dist-info/METADATA
gemini_unwatermark-0.1.1.dist-info/WHEEL
gemini_unwatermark-0.1.1.dist-info/entry_points.txt
gemini_unwatermark-0.1.1.dist-info/licenses/LICENSE
gemini_unwatermark-0.1.1.dist-info/RECORD
