Metadata-Version: 2.4
Name: gemini-unwatermark
Version: 0.1.1
Summary: Remove watermarks from Gemini-generated images using LaMa inpainting
Project-URL: Homepage, https://github.com/jaylann/gemini-unwatermark
Project-URL: Repository, https://github.com/jaylann/gemini-unwatermark
Author: Justin Lanfermann
License-Expression: Apache-2.0
License-File: LICENSE
Keywords: ai,gemini,image-processing,inpainting,lama,watermark
Classifier: Development Status :: 4 - Beta
Classifier: Environment :: Console
Classifier: Intended Audience :: End Users/Desktop
Classifier: License :: OSI Approved :: Apache Software License
Classifier: Programming Language :: Python :: 3.10
Classifier: Programming Language :: Python :: 3.11
Classifier: Programming Language :: Python :: 3.12
Classifier: Programming Language :: Python :: 3.13
Classifier: Topic :: Multimedia :: Graphics
Requires-Python: <3.14,>=3.10
Requires-Dist: httpx>=0.25.0
Requires-Dist: numpy>=1.24.0
Requires-Dist: onnxruntime>=1.16.0
Requires-Dist: pillow>=10.0.0
Requires-Dist: rich>=13.0.0
Requires-Dist: typer>=0.9.0
Provides-Extra: gpu
Requires-Dist: onnxruntime-gpu>=1.16.0; extra == 'gpu'
